head_switcher/__init__.py
head_switcher/cli.py
head_switcher/core.py
head_switcher/install.py
head_switcher-0.0.2.dist-info/METADATA
head_switcher-0.0.2.dist-info/WHEEL
head_switcher-0.0.2.dist-info/entry_points.txt
head_switcher-0.0.2.dist-info/RECORD
