Metadata-Version: 2.3
Name: head_switcher
Version: 0.0.2
Summary: Help you load frontend asset into your headless flask app without using static folder config.
Project-URL: Homepage, https://github.com/dataset-sh/head_switcher
Project-URL: Bug Tracker, https://github.com/dataset-sh/head_switcher/issues
Author-email: Hao Wu <haowu@dataset.sh>
License: MIT License
Classifier: License :: OSI Approved :: MIT License
Classifier: Operating System :: OS Independent
Classifier: Programming Language :: Python :: 3
Requires-Python: >=3.9
